[
  {
    "id": 1,
    "title": "제목 1",
    "likes": 10,
    "comments": 5,
    "views": 100,
    "author": "작성자 1",
    "date": "2024-02-16 12:30:00",
    "profileImage": "/image/Cha.png"
  },
  {
    "id": 2,
    "title": "제목 2",
    "likes": 5,
    "comments": 2,
    "views": 50,
    "author": "작성자 2",
    "date": "2024-02-16 13:45:00",
    "profileImage": "/image/Chu.png"
  },
  {
    "id": 3,
    "title": "제목 3",
    "likes": 8,
    "comments": 4,
    "views": 80,
    "author": "작성자 3",
    "date": "2024-02-16 14:00:00",
    "profileImage": "/image/Mashiro.png"
  },
  {
    "id": 4,
    "title": "제목 4",
    "likes": 8,
    "comments": 4,
    "views": 80,
    "author": "작성자 4",
    "date": "2024-02-16 14:00:00",
    "profileImage": "/image/Liz.png"
  },
  {
    "id": 5,
    "title": "제목 5",
    "likes": 8,
    "comments": 5,
    "views": 80,
    "author": "작성자 5",
    "date": "2024-02-16 15:00:00",
    "profileImage": "/image/LizStage.png"
  },
  {
    "id": 6,
    "title": "제목 6",
    "likes": 8,
    "comments": 6,
    "views": 80,
    "author": "작성자 6",
    "date": "2024-02-16 16:00:00",
    "profileImage": "/image/RemRam.png"
  },
  {
    "id": 7,
    "title": "제목 7",
    "likes": 8,
    "comments": 7,
    "views": 80,
    "author": "작성자 7",
    "date": "2024-02-16 14:00:00",
    "profileImage": "/image/Kana.png"
  }
]
